igs_toolbox/__init__.py
igs_toolbox/file_utils.py
igs_toolbox/log_utils.py
igs_toolbox/py.typed
igs_toolbox/version_utils.py
igs_toolbox/converters/__init__.py
igs_toolbox/converters/convert_seq_metadata.py
igs_toolbox/extractor/__init__.py
igs_toolbox/extractor/read_qr.py
igs_toolbox/extractor/res/extractor_sample_a.pdf
igs_toolbox/extractor/res/extractor_sample_b.pdf
igs_toolbox/extractor/res/extractor_sample_c.pdf
igs_toolbox/formatChecker/__init__.py
igs_toolbox/formatChecker/json_checker.py
igs_toolbox/formatChecker/res/isolation_source/json/materialACBP.json
igs_toolbox/formatChecker/res/isolation_source/json/materialCVDP.json
igs_toolbox/formatChecker/res/isolation_source/json/materialEBCP.json
igs_toolbox/formatChecker/res/isolation_source/json/materialEHCP.json
igs_toolbox/formatChecker/res/isolation_source/json/materialHAVP.json
igs_toolbox/formatChecker/res/isolation_source/json/materialHEVP.json
igs_toolbox/formatChecker/res/isolation_source/json/materialINVP.json
igs_toolbox/formatChecker/res/isolation_source/json/materialLEGP.json
igs_toolbox/formatChecker/res/isolation_source/json/materialLISP.json
igs_toolbox/formatChecker/res/isolation_source/json/materialMRAP.json
igs_toolbox/formatChecker/res/isolation_source/json/materialMSVP.json
igs_toolbox/formatChecker/res/isolation_source/json/materialMYTP.json
igs_toolbox/formatChecker/res/isolation_source/json/materialNEIP.json
igs_toolbox/formatChecker/res/isolation_source/json/materialSALP.json
igs_toolbox/formatChecker/res/isolation_source/json/materialSPNP.json
igs_toolbox/formatChecker/res/isolation_source/json/materialSTYP.json
igs_toolbox/formatChecker/res/isolation_source/json/materialWNVP.json
igs_toolbox/formatChecker/res/isolation_source/txt/valueSetACBP.txt
igs_toolbox/formatChecker/res/isolation_source/txt/valueSetCDFP.txt
igs_toolbox/formatChecker/res/isolation_source/txt/valueSetCVDP.txt
igs_toolbox/formatChecker/res/isolation_source/txt/valueSetEBCP.txt
igs_toolbox-1.7.3.dist-info/LICENSE
igs_toolbox-1.7.3.dist-info/METADATA
igs_toolbox-1.7.3.dist-info/WHEEL
igs_toolbox-1.7.3.dist-info/entry_points.txt
igs_toolbox-1.7.3.dist-info/top_level.txt
igs_toolbox-1.7.3.dist-info/RECORD
