Metadata-Version: 2.1
Name: igs-toolbox
Version: 1.7.3
Summary: A toolbox to check whether files follow a predefined schema.
Author-email: IGS Developers <IGS-Developers@rki.de>
License: The MIT License (MIT)
Project-URL: Homepage, https://www.rki.de/DE/Content/Infekt/IGS/IGS_node.html
Requires-Python: >=3.8
License-File: LICENSE
Requires-Dist: jsonschema >=4.22.0
Requires-Dist: pandas >=2.0.0
Requires-Dist: pdf2image >=1.16.3
Requires-Dist: opencv-python >=4.8.0.7
Requires-Dist: typer >=0.12.3
Requires-Dist: openpyxl >=3.1.2
Requires-Dist: rfc3339-validator >=0.1.4
Requires-Dist: typing-extensions ; python_version < "3.10"
Requires-Dist: backports.zoneinfo ; python_version < "3.9"
Provides-Extra: dev
Requires-Dist: mypy ; extra == 'dev'
Requires-Dist: ruff ; extra == 'dev'
Requires-Dist: pytest ; extra == 'dev'
Requires-Dist: pytest-cov ; extra == 'dev'
Requires-Dist: types-jsonschema ; extra == 'dev'
Requires-Dist: pandas-stubs ; extra == 'dev'
